setup.py
gau_bino_distributions/Binomialdistribution.py
gau_bino_distributions/Gaussiandistribution.py
gau_bino_distributions/Generaldistribution.py
gau_bino_distributions/__init__.py
gau_bino_distributions.egg-info/PKG-INFO
gau_bino_distributions.egg-info/SOURCES.txt
gau_bino_distributions.egg-info/dependency_links.txt
gau_bino_distributions.egg-info/not-zip-safe
gau_bino_distributions.egg-info/top_level.txt