Metadata-Version: 1.0
Name: gau-bino-distributions
Version: 0.7
Summary: Gaussian and Binomial Distributions
Home-page: UNKNOWN
Author: Hao Xu
Author-email: edifierxuhao123@gmail.com
License: UNKNOWN
Platform: UNKNOWN
